github_backup/__init__.py
github_backup/__main__.py
github_backup/cli.py
github_backup/github_backup.py
github_backup-0.61.3.dist-info/licenses/LICENSE.txt
github_backup-0.61.3.dist-info/METADATA
github_backup-0.61.3.dist-info/WHEEL
github_backup-0.61.3.dist-info/entry_points.txt
github_backup-0.61.3.dist-info/top_level.txt
github_backup-0.61.3.dist-info/zip-safe
github_backup-0.61.3.dist-info/RECORD
