Metadata-Version: 2.4
Name: github-backup
Version: 0.61.3
Summary: backup a github user or organization
Home-page: http://github.com/josegonzalez/python-github-backup
Author: Jose Diaz-Gonzalez
Author-email: github-backup@josediazgonzalez.com
License: MIT
Classifier: Development Status :: 5 - Production/Stable
Classifier: Topic :: System :: Archiving :: Backup
Classifier: License :: OSI Approved :: MIT License
Classifier: Programming Language :: Python :: 3.10
Classifier: Programming Language :: Python :: 3.11
Classifier: Programming Language :: Python :: 3.12
Classifier: Programming Language :: Python :: 3.13
Classifier: Programming Language :: Python :: 3.14
Requires-Python: >=3.10
License-File: LICENSE.txt
Dynamic: author
Dynamic: author-email
Dynamic: classifier
Dynamic: description
Dynamic: description-content-type
Dynamic: home-page
Dynamic: license
Dynamic: license-file
Dynamic: requires-python
Dynamic: summary
